gan_package/__init__.py
gan_package/dataloader.py
gan_package/main.py
gan_package/models.py
gan_package/testing.py
gan_package/train.py
gan_package/utils.py
GANsforVirtualEye-0.1.2.dist-info/LICENSE
GANsforVirtualEye-0.1.2.dist-info/METADATA
GANsforVirtualEye-0.1.2.dist-info/WHEEL
GANsforVirtualEye-0.1.2.dist-info/top_level.txt
GANsforVirtualEye-0.1.2.dist-info/RECORD
